{
  "questions": [
    {
      "id": "1301",
      "namespace": "probe-lab",
      "machineHostname": "ckad9999",
      "question": "A Deployment named `health-api` in namespace `probe-lab` is failing because its HTTP probe wiring is wrong.\n\nFix the workload so that:\n- the container keeps port `8080`\n- `startupProbe`, `livenessProbe`, and `readinessProbe` all check path `/healthz`\n- each HTTP probe targets port `8080`\n- the Deployment becomes Available\n- the running container serves `ok` at `http://127.0.0.1:8080/healthz`\n\nDo not replace the container image. Fix the Deployment probe configuration in place.",
      "concepts": [
        "readinessProbe",
        "livenessProbe",
        "startupProbe",
        "operations",
        "troubleshooting"
      ],
      "verification": [
        {
          "id": "1",
          "description": "Deployment health-api uses the intended container port and HTTP probe paths",
          "verificationScriptFile": "1301_s1_validate_probe_spec.sh",
          "expectedOutput": "0",
          "weightage": 2
        },
        {
          "id": "2",
          "description": "Deployment health-api becomes Available after the probe wiring is repaired",
          "verificationScriptFile": "1301_s2_validate_probe_rollout.sh",
          "expectedOutput": "0",
          "weightage": 3
        },
        {
          "id": "3",
          "description": "The running container serves ok at the repaired /healthz endpoint",
          "verificationScriptFile": "1301_s3_validate_probe_endpoint.sh",
          "expectedOutput": "0",
          "weightage": 2
        }
      ]
    }
  ]
}
