{
  "questions": [
    {
      "id": "2601",
      "namespace": "envfrom-lab",
      "machineHostname": "ckad9999",
      "question": "A Deployment named `env-bundle` in namespace `envfrom-lab` is failing because its envFrom wiring is wrong.\n\nFix the workload so that:\n- the container remains named `api`\n- the image remains `busybox:1.36`\n- the ConfigMap envFrom source is `app-env`\n- the Secret envFrom source is `app-secret`\n- the Secret envFrom prefix is `SECRET_`\n- the Deployment becomes Available\n- the running container sees `MODE=production` and `SECRET_API_KEY=stable-key`\n\nDo not inline the environment values directly into `env:` entries. Repair the envFrom sources in place.",
      "concepts": [
        "configMap",
        "secret",
        "envFrom",
        "troubleshooting"
      ],
      "verification": [
        {
          "id": "1",
          "description": "Deployment env-bundle uses the intended container name, image, envFrom sources, and Secret prefix",
          "verificationScriptFile": "2601_s1_validate_envfrom_spec.sh",
          "expectedOutput": "0",
          "weightage": 2
        },
        {
          "id": "2",
          "description": "Deployment env-bundle becomes Available after the envFrom wiring is repaired",
          "verificationScriptFile": "2601_s2_validate_envfrom_rollout.sh",
          "expectedOutput": "0",
          "weightage": 3
        },
        {
          "id": "3",
          "description": "The running container reads the expected ConfigMap and Secret-backed environment variables",
          "verificationScriptFile": "2601_s3_validate_envfrom_env.sh",
          "expectedOutput": "0",
          "weightage": 2
        }
      ]
    }
  ]
}
